<?xml version="1.0" encoding="UTF-8" standalone="yes"?>
<persistence version="2.0" 
			 xmlns="http://java.sun.com/xml/ns/persistence" 
			 xmlns:xsi="http://www.w3.org/2001/XMLSchema-instance" 
			 xsi:schemaLocation="http://java.sun.com/xml/ns/persistence http://java.sun.com/xml/ns/persistence/persistence_2_0.xsd">
	<persistence-unit name="Hermes">
		<jta-data-source>hermesDS-JTA</jta-data-source>
		<non-jta-data-source>hermesDS-Non-JTA</non-jta-data-source>
		 <properties>
            <property name="openjpa.jdbc.DBDictionary" value="mysql"/>
         </properties>
	</persistence-unit>
</persistence>